MANIFEST.in
README.md
setup.cfg
setup.py
sql_to_graphite/__init__.py
sql_to_graphite.egg-info/PKG-INFO
sql_to_graphite.egg-info/SOURCES.txt
sql_to_graphite.egg-info/dependency_links.txt
sql_to_graphite.egg-info/entry_points.txt
sql_to_graphite.egg-info/requires.txt
sql_to_graphite.egg-info/top_level.txt
sql_to_graphite.egg-info/zip-safe