Metadata-Version: 1.0
Name: sql-to-graphite
Version: 0.0.5
Summary: A tool to send SQL results to Graphite
Home-page: http://github.com/philipcristiano/sql-to-graphite
Author: Philip Cristiano
Author-email: philipcristiano@gmail.com
License: BSD
Keywords: SQL Graphite
Platform: UNKNOWN
